odc_typer_test/__init__.py
odc_typer_test/main.py
odc_typer_test-0.3.0.dist-info/entry_points.txt
odc_typer_test-0.3.0.dist-info/WHEEL
odc_typer_test-0.3.0.dist-info/METADATA
odc_typer_test-0.3.0.dist-info/RECORD
